LICENSE.txt
MANIFEST.in
README.rst
requirements.txt
setup.py
metaseq/__init__.py
metaseq/_genomic_signal.py
metaseq/array_helpers.py
metaseq/arrayify.py
metaseq/colormap_adjust.py
metaseq/filetype_adapters.py
metaseq/helpers.py
metaseq/minibrowser.py
metaseq/persistence.py
metaseq/plotutils.py
metaseq/rebin_naive.py
metaseq/results_table.py
metaseq/tableprinter.py
metaseq/version.py
metaseq.egg-info/PKG-INFO
metaseq.egg-info/SOURCES.txt
metaseq.egg-info/dependency_links.txt
metaseq.egg-info/requires.txt
metaseq.egg-info/top_level.txt
metaseq/integration/__init__.py
metaseq/integration/chipseq.py
metaseq/integration/signal_comparison.py
metaseq/scripts/download_metaseq_example_data.py
metaseq/scripts/metaseq-cli
metaseq/scripts/speedtest.py
metaseq/test/__init__.py
metaseq/test/test.py
metaseq/test/test_large.py
metaseq/test/test_results_table.py
metaseq/test/data/__init__.py
metaseq/test/data/gdc.bam
metaseq/test/data/gdc.bam.bai
metaseq/test/data/gdc.bed
metaseq/test/data/gdc.bed.gz
metaseq/test/data/gdc.bed.gz.tbi
metaseq/test/data/gdc.bedgraph
metaseq/test/data/gdc.bigbed
metaseq/test/data/gdc.bigwig
metaseq/test/data/make_examples_from_pybedtools.py
metaseq/test/data/x.bam
metaseq/test/data/x.bam.bai
metaseq/test/data/x.bed.gz
metaseq/test/data/x.bed.gz.tbi
metaseq/test/data/x.bigbed
metaseq/test/data/x.bigwig