Metadata-Version: 1.1
Name: metaseq
Version: 0.5.6
Summary: Integrative analysis of high-thoughput sequencing data
Home-page: http://github.com/daler/metaseq
Author: Ryan Dale
Author-email: dalerr@niddk.nih.gov
License: MIT
Platform: UNKNOWN
Classifier: Development Status :: 4 - Beta
Classifier: Intended Audience :: Science/Research
Classifier: Intended Audience :: Developers
Classifier: Intended Audience :: System Administrators
Classifier: Operating System :: POSIX
Classifier: Operating System :: MacOS :: MacOS X
Classifier: Environment :: Console
Classifier: License :: OSI Approved :: MIT License
Classifier: Topic :: Scientific/Engineering :: Bio-Informatics
Classifier: Topic :: Scientific/Engineering :: Medical Science Apps.
